Metadata-Version: 2.1
Name: django-watermarks
Version: 2.0.1
Summary: Django watermarks app
Home-page: https://github.com/pmaigutyak/mp-watermarks
Author: Paul Maigutyak
Author-email: pmaigutyak@gmail.com
License: MIT
Download-URL: https://github.com/pmaigutyak/mp-watermarks/archive/2.0.1.tar.gz
Platform: UNKNOWN
License-File: LICENSE
